dtacs/__init__.py
dtacs/download_weights.py
dtacs/model_wrapper.py
dtacs/nn.py
dtacs/plot.py
dtacs-1.0.1.dist-info/LICENSE
dtacs-1.0.1.dist-info/METADATA
dtacs-1.0.1.dist-info/WHEEL
dtacs-1.0.1.dist-info/RECORD
