Metadata-Version: 2.1
Name: dtacs
Version: 1.0.1
Summary: 🛰️ Cloud Detection and Atmospheric Correction With Efficient Deep Learning Models
Home-page: https://github.com/spaceml-org/DTACSNet
License: 	GPL-3.0
Author: Gonzalo Mateo-García
Requires-Python: >=3.10,<4.0
Classifier: License :: Other/Proprietary License
Classifier: Programming Language :: Python :: 3
Classifier: Programming Language :: Python :: 3.10
Classifier: Programming Language :: Python :: 3.11
Classifier: Programming Language :: Python :: 3.12
Classifier: Programming Language :: Python :: 3.13
Requires-Dist: numpy (>=1)
Requires-Dist: rasterio (>=1)
Requires-Dist: requests (>=2.32.3,<3.0.0)
Requires-Dist: segmentation-models-pytorch (>=0.3.4,<0.4.0)
Requires-Dist: torch (>=2.5.1,<3.0.0)
Requires-Dist: tqdm (>=4.67.1,<5.0.0)
Project-URL: Documentation, https://spaceml-org.github.io/DTACSNet/
Project-URL: Repository, https://github.com/spaceml-org/DTACSNet
